wikitextparser/__init__.py
wikitextparser/_argument.py
wikitextparser/_cell.py
wikitextparser/_comment_bold_italic.py
wikitextparser/_config.py
wikitextparser/_externallink.py
wikitextparser/_parameter.py
wikitextparser/_parser_function.py
wikitextparser/_section.py
wikitextparser/_spans.py
wikitextparser/_table.py
wikitextparser/_tag.py
wikitextparser/_template.py
wikitextparser/_wikilink.py
wikitextparser/_wikilist.py
wikitextparser/_wikitext.py
wikitextparser-0.56.4.dist-info/licenses/LICENSE.md
wikitextparser-0.56.4.dist-info/WHEEL
wikitextparser-0.56.4.dist-info/METADATA
wikitextparser-0.56.4.dist-info/RECORD
