Metadata-Version: 2.4
Name: wikitextparser
Version: 0.56.4
Summary: A simple parsing tool for MediaWiki's wikitext markup.
Keywords: MediaWiki,wikitext,parser
Author-email: 5j9 <5j9@users.noreply.github.com>
Requires-Python: >= 3.8
Classifier: Programming Language :: Python
Classifier: License :: OSI Approved :: GNU General Public License v3 (GPLv3)
Classifier: Topic :: Text Processing
License-File: LICENSE.md
Requires-Dist: regex >= 2022.9.11
Requires-Dist: wcwidth
Requires-Dist: coverage ; extra == "dev"
Requires-Dist: pytest ; extra == "tests"
Project-URL: Homepage, https://github.com/5j9/wikitextparser
Provides-Extra: dev
Provides-Extra: tests
